niel/client/__init__.py
niel/client/line.py
niel/commands/__init__.py
niel/commands/auth.py
niel/commands/create.py
niel/commands/default.py
niel/commands/drop.py
niel/commands/image.py
niel/commands/link.py
niel/commands/set_default.py
niel/commands/unlink.py
niel/core.py
niel/types/__init__.py
niel/types/action.py
niel/types/area.py
niel/types/bounds.py
niel/types/rich_menu.py
niel/types/size.py
niel-0.1.0.dist-info/METADATA
niel-0.1.0.dist-info/WHEEL
niel-0.1.0.dist-info/entry_points.txt
niel-0.1.0.dist-info/RECORD
